dvg_qdeviceio.py
dvg_qdeviceio-1.6.0.dist-info/AUTHORS.rst
dvg_qdeviceio-1.6.0.dist-info/LICENSE.txt
dvg_qdeviceio-1.6.0.dist-info/METADATA
dvg_qdeviceio-1.6.0.dist-info/WHEEL
dvg_qdeviceio-1.6.0.dist-info/top_level.txt
dvg_qdeviceio-1.6.0.dist-info/RECORD
