Metadata-Version: 2.1
Name: dvg-qdeviceio
Version: 1.6.0
Summary: Hassle-free PyQt/PySide interface for multithreaded data acquisition and communication with an I/O device.
Home-page: https://python-dvg-qdeviceio.readthedocs.io/
Author: Dennis van Gils
Author-email: vangils.dennis@gmail.com
License: MIT
Project-URL: Issue Tracker, https://github.com/Dennis-van-Gils/python-dvg-qdeviceio/issues
Keywords: PyQt5,PyQt6,PySide2,PySide6,multithread,device I/O,automation,laboratory,science
Classifier: Development Status :: 5 - Production/Stable
Classifier: License :: OSI Approved :: MIT License
Classifier: Intended Audience :: Developers
Classifier: Intended Audience :: Science/Research
Classifier: Operating System :: OS Independent
Classifier: Programming Language :: Python
Classifier: Programming Language :: Python :: 3
Classifier: Topic :: Scientific/Engineering :: Electronic Design Automation (EDA)
Classifier: Topic :: Software Development :: Libraries :: Application Frameworks
Requires-Python: >=3.6
License-File: LICENSE.txt
License-File: AUTHORS.rst
Requires-Dist: dvg-debug-functions ~=2.5
Requires-Dist: numpy <3.0,>=1.15
Requires-Dist: qtpy
